textslinger/__init__.py
textslinger/causal.py
textslinger/classifier.py
textslinger/exceptions.py
textslinger/language_model.py
textslinger/mixture.py
textslinger/ngram.py
textslinger/uniform.py
textslinger-0.1.1.dist-info/licenses/LICENSE.md
textslinger-0.1.1.dist-info/METADATA
textslinger-0.1.1.dist-info/WHEEL
textslinger-0.1.1.dist-info/top_level.txt
textslinger-0.1.1.dist-info/zip-safe
textslinger-0.1.1.dist-info/RECORD
