Metadata-Version: 2.4
Name: textslinger
Version: 0.1.1
Summary: TextSlinger text prediction toolkit.
Author-email: Dylan Gaines <dcgaines@mtu.edu>, Keith Vertanen <vertanen@mtu.edu>, CAMBI <cambi_support@googlegroups.com>
License: MIT License
Project-URL: Homepage, https://www.cambi.tech/
Project-URL: Source, https://github.com/kdv123/textpredict
Platform: Linux
Platform: Windows
Platform: Mac OS-X
Classifier: License :: OSI Approved :: MIT License
Classifier: Topic :: Scientific/Engineering :: Human Machine Interfaces
Classifier: Natural Language :: English
Classifier: Intended Audience :: Science/Research
Classifier: Intended Audience :: End Users/Desktop
Classifier: Intended Audience :: Developers
Classifier: Programming Language :: Python
Classifier: Programming Language :: Python :: 3.9
Classifier: Programming Language :: Python :: 3.10
Requires-Python: <3.11,>=3.9
License-File: LICENSE.md
Requires-Dist: torch==2.2.0
Requires-Dist: torchvision==0.17.0
Requires-Dist: torchaudio==2.2.0
Requires-Dist: datasets==2.0.0
Requires-Dist: bitsandbytes==0.42.0
Requires-Dist: requests==2.32.3
Requires-Dist: kenlm==0.1
Requires-Dist: nlpaug==1.1.11
Requires-Dist: psutil==5.7.2
Requires-Dist: ipywidgets==8.1.3
Requires-Dist: sentencepiece==0.2.0
Requires-Dist: protobuf==4.25.3
Requires-Dist: evaluate==0.4.0
Requires-Dist: scikit-learn==1.2.2
Requires-Dist: accelerate==0.33.0
Requires-Dist: transformers==4.47.0
Requires-Dist: numpy==1.24.4
Requires-Dist: tqdm==4.62.2
Provides-Extra: release
Requires-Dist: twine==5.0.0; extra == "release"
Requires-Dist: build==1.2.2.post1; extra == "release"
Requires-Dist: wheel==0.43.0; extra == "release"
Dynamic: license-file
